dcstatus/__init__.py
dcstatus/__main__.py
dcstatus/changelog.py
dcstatus/constants.py
dcstatus/hooks.py
dcstatus/microsoft.py
dcstatus/status.py
dcstatus/stores.py
dcstatus/web.py
dcstatus-1.4.0.dist-info/licenses/LICENSE
dcstatus-1.4.0.dist-info/METADATA
dcstatus-1.4.0.dist-info/WHEEL
dcstatus-1.4.0.dist-info/entry_points.txt
dcstatus-1.4.0.dist-info/top_level.txt
dcstatus-1.4.0.dist-info/RECORD
