Metadata-Version: 2.4
Name: dcstatus
Version: 1.4.0
Summary: Bot to get Delta Chat releases status information
Author-email: adbenitez <adb@merlinux.eu>
Project-URL: Homepage, https://github.com/deltachat-bot/dcstatus
Keywords: deltachat,bot
Classifier: Development Status :: 4 - Beta
Classifier: Programming Language :: Python :: 3
Classifier: License :: OSI Approved :: GNU General Public License v3 or later (GPLv3+)
Requires-Python: >=3.10
License-File: LICENSE
Requires-Dist: deltabot-cli<7.0,>=6.0.0
Requires-Dist: cachelib>=0.13.0
Requires-Dist: requests>=2.32.3
Requires-Dist: beautifulsoup4<5.0,>=4.12.3
Requires-Dist: playwright<2.0,>=1.48.0
Provides-Extra: dev
Requires-Dist: black; extra == "dev"
Requires-Dist: mypy; extra == "dev"
Requires-Dist: isort; extra == "dev"
Requires-Dist: pylint; extra == "dev"
Requires-Dist: pylama; extra == "dev"
Requires-Dist: pytest; extra == "dev"
Requires-Dist: types-requests; extra == "dev"
Dynamic: license-file
